mp3monitoring/__init__.py
mp3monitoring/__main__.py
mp3monitoring/main.py
mp3monitoring/static_data.py
mp3monitoring/tools.py
mp3monitoring/core/__init__.py
mp3monitoring/core/job.py
mp3monitoring/core/manager.py
mp3monitoring/core/settings.py
mp3monitoring/core/signal/__init__.py
mp3monitoring/core/signal/_signal_no_qt.py
mp3monitoring/core/signal/_signal_qt.py
mp3monitoring/gui/__init__.py
mp3monitoring/gui/monitor_table_model.py
mp3monitoring/gui/stop_thread.py
mp3monitoring/gui/updater.py
mp3monitoring/gui/vertical_tab_bar.py
mp3monitoring/gui/dialog/__init__.py
mp3monitoring/gui/dialog/about.py
mp3monitoring/gui/dialog/add_job.py
mp3monitoring/gui/dialog/settings.py
mp3monitoring/gui/dialog/show.py
mp3monitoring/gui/pkg_data/__init__.py
mp3monitoring/gui/pkg_data/logo.ico
mp3monitoring/gui/pkg_data/logo.svg
mp3monitoring/gui/pkg_data/symbols/__init__.py
mp3monitoring/gui/pkg_data/symbols/add.svg
mp3monitoring/gui/pkg_data/symbols/error.svg
mp3monitoring/gui/pkg_data/symbols/info.svg
mp3monitoring/gui/pkg_data/symbols/license.rst
mp3monitoring/gui/pkg_data/symbols/ok.svg
mp3monitoring/gui/pkg_data/symbols/power.svg
mp3monitoring/gui/pkg_data/symbols/remove.svg
mp3monitoring/gui/pkg_data/symbols/search.svg
mp3monitoring/gui/pkg_data/symbols/settings.svg
mp3monitoring/gui/pkg_data/symbols/start.svg
mp3monitoring/gui/pkg_data/symbols/stop.svg
mp3monitoring/gui/pkg_data/symbols/stopped.svg
mp3monitoring/gui/pkg_data/symbols/wait.svg
mp3monitoring/gui/pkg_data/symbols/warning.svg
mp3monitoring/gui/ui/__init__.py
mp3monitoring/gui/ui/about_dialog.py
mp3monitoring/gui/ui/add_job_dialog.py
mp3monitoring/gui/ui/main.py
mp3monitoring/gui/ui/settings_dialog.py
mp3monitoring/gui/ui/shutdown_overlay.py
mp3monitoring/gui/widget/__init__.py
mp3monitoring/gui/widget/shutdown_overlay.py
mp3monitoring/gui/widget/wait_animation.py
mp3monitoring/gui/window/__init__.py
mp3monitoring/gui/window/main.py
mp3monitoring-2.0.0.dist-info/LICENSE.md
mp3monitoring-2.0.0.dist-info/METADATA
mp3monitoring-2.0.0.dist-info/WHEEL
mp3monitoring-2.0.0.dist-info/entry_points.txt
mp3monitoring-2.0.0.dist-info/top_level.txt
mp3monitoring-2.0.0.dist-info/zip-safe
mp3monitoring-2.0.0.dist-info/RECORD
