Metadata-Version: 2.1
Name: mp3monitoring
Version: 2.0.0
Summary: Monitors a folder and copies mp3s to another folder.
Home-page: https://github.com/IceflowRE/mp3monitoring
Author: Iceflower S
Author-email: iceflower@gmx.de
License: GPLv3
Keywords: mp3 monitoring
Platform: UNKNOWN
Classifier: Programming Language :: Python :: 3.8
Classifier: License :: OSI Approved :: GNU General Public License v3 (GPLv3)
Classifier: Development Status :: 5 - Production/Stable
Classifier: Operating System :: OS Independent
Classifier: Intended Audience :: End Users/Desktop
Classifier: Natural Language :: English
Classifier: Environment :: Console
Classifier: Environment :: X11 Applications :: Qt
Requires-Python: >=3.9
Requires-Dist: mutagen (>=1.45.1)
Requires-Dist: packaging (>=20.4)
Provides-Extra: dev
Requires-Dist: flake8 (>=3.8.3) ; extra == 'dev'
Requires-Dist: pylint (>=2.6.0) ; extra == 'dev'
Requires-Dist: pyroma (>=2.6) ; extra == 'dev'
Requires-Dist: pytest (>=6.0.1) ; extra == 'dev'
Requires-Dist: pytest-cov (>=2.10.1) ; extra == 'dev'
Requires-Dist: setuptools (>=50.3.0) ; extra == 'dev'
Requires-Dist: Sphinx (>=3.2.1) ; extra == 'dev'
Requires-Dist: sphinx-autodoc-typehints (>=1.11.0) ; extra == 'dev'
Requires-Dist: sphinx-rtd-theme (>=0.5.0) ; extra == 'dev'
Requires-Dist: twine (>=3.2.0) ; extra == 'dev'
Requires-Dist: wheel (>=0.35.1) ; extra == 'dev'
Provides-Extra: gui
Requires-Dist: pyside2 (>=5.15.1) ; extra == 'gui'
Requires-Dist: pylnk3 (>=0.4.2) ; extra == 'gui'
Requires-Dist: urllib3[secure] (>=1.25.10) ; extra == 'gui'
